{"series": [{"data": [{"x": "aquatic_plants_and sea-grass", "y": 15.12}, {"x": "fish_and_vertebrates", "y": 11.79}, {"x": "human_divers", "y": 7.54}, {"x": "reefs_and_invertebrates", "y": 52.31}, {"x": "robots", "y": 4.74}, {"x": "sea-floor_and_rocks", "y": 34.77}, {"x": "waterbody", "y": 37.54}, {"x": "wrecks_and_ruins", "y": 41.85}]}], "options": {"chart": {"type": "treemap", "height": 470}, "legend": {"show": false}, "plotOptions": {"treemap": {"distributed": true, "enableShades": false}}, "title": {"text": "Average area of class objects on image", "align": "left"}, "colors": ["#00ff00", "#ffff00", "#0000ff", "#ff00ff", "#ff0000", "#ffffff", "#000000", "#00ffff"], "tooltip": {"y": {}}}, "type": "treemap", "height": 350, "sly_options": {"tooltip": "Average area of class objects on image is {y}%"}}